<slides>
    <slide type="imageOnly">
        <image src="/path/image.jpg"></image>
    </slide>

    <slide type="imageWithTitle">
        <image src="/assets/images.jpg"></image>
        <title>Dit is een titel</title>
    </slide>

    <slide type="bullets">
        <title>Dit is een titel</title>
        <bullet>Dit is een bullet</bullet>
        <bullet>Dit is een bullet</bullet>
        <bullet>Dit is een bullet</bullet>
        <bullet>Dit is een bullet</bullet>
    </slide>

    <slide type="title">
        <title>Dit is een titel</title>
    </slide>

</slides>